{
    "original": {
        "CT": {
            "test": {
                "MisclassificationRate": 0.1881881881881882,
                "MulticlassPrecision{MLJBase.MacroAvg, OrderedCollections.LittleDict}": 0.8160732500451394,
                "MulticlassTruePositiveRate{MLJBase.MacroAvg, OrderedCollections.LittleDict}": 0.8118118118118117
            },
            "train": {
                "MisclassificationRate": 0.0,
                "MulticlassPrecision{MLJBase.MacroAvg, OrderedCollections.LittleDict}": 1.0,
                "MulticlassTruePositiveRate{MLJBase.MacroAvg, OrderedCollections.LittleDict}": 1.0
            }
        },
        "LDA": {
            "test": {
                "MisclassificationRate": 0.34634634634634637,
                "MulticlassPrecision{MLJBase.MacroAvg, OrderedCollections.LittleDict}": 0.6543777543777545,
                "MulticlassTruePositiveRate{MLJBase.MacroAvg, OrderedCollections.LittleDict}": 0.6536536536536537
            },
            "train": {
                "MisclassificationRate": 0.0,
                "MulticlassPrecision{MLJBase.MacroAvg, OrderedCollections.LittleDict}": 1.0,
                "MulticlassTruePositiveRate{MLJBase.MacroAvg, OrderedCollections.LittleDict}": 1.0
            }
        }
    },
    "ldbk": {
        "CT": {
            "test": {
                "MisclassificationRate": 0.1001001001001001,
                "MulticlassPrecision{MLJBase.MacroAvg, OrderedCollections.LittleDict}": 0.8998856276728514,
                "MulticlassTruePositiveRate{MLJBase.MacroAvg, OrderedCollections.LittleDict}": 0.8998998998998999
            },
            "train": {
                "MisclassificationRate": 0.0,
                "MulticlassPrecision{MLJBase.MacroAvg, OrderedCollections.LittleDict}": 1.0,
                "MulticlassTruePositiveRate{MLJBase.MacroAvg, OrderedCollections.LittleDict}": 1.0
            }
        },
        "LDA": {
            "test": {
                "MisclassificationRate": 0.13613613613613615,
                "MulticlassPrecision{MLJBase.MacroAvg, OrderedCollections.LittleDict}": 0.8692666675097798,
                "MulticlassTruePositiveRate{MLJBase.MacroAvg, OrderedCollections.LittleDict}": 0.8638638638638639
            },
            "train": {
                "MisclassificationRate": 0.10101010101010101,
                "MulticlassPrecision{MLJBase.MacroAvg, OrderedCollections.LittleDict}": 0.9011904761904762,
                "MulticlassTruePositiveRate{MLJBase.MacroAvg, OrderedCollections.LittleDict}": 0.8989898989898991
            }
        }
    },
    "ldbkash": {
        "CT": {
            "test": {
                "MisclassificationRate": 0.3333333333333333,
                "MulticlassPrecision{MLJBase.MacroAvg, OrderedCollections.LittleDict}": 0.6685060284296318,
                "MulticlassTruePositiveRate{MLJBase.MacroAvg, OrderedCollections.LittleDict}": 0.6666666666666666
            },
            "train": {
                "MisclassificationRate": 0.0,
                "MulticlassPrecision{MLJBase.MacroAvg, OrderedCollections.LittleDict}": 1.0,
                "MulticlassTruePositiveRate{MLJBase.MacroAvg, OrderedCollections.LittleDict}": 1.0
            }
        },
        "LDA": {
            "test": {
                "MisclassificationRate": 0.4544544544544545,
                "MulticlassPrecision{MLJBase.MacroAvg, OrderedCollections.LittleDict}": 0.5524094224335965,
                "MulticlassTruePositiveRate{MLJBase.MacroAvg, OrderedCollections.LittleDict}": 0.5455455455455456
            },
            "train": {
                "MisclassificationRate": 0.2727272727272727,
                "MulticlassPrecision{MLJBase.MacroAvg, OrderedCollections.LittleDict}": 0.7293731231231231,
                "MulticlassTruePositiveRate{MLJBase.MacroAvg, OrderedCollections.LittleDict}": 0.7272727272727272
            }
        }
    },
    "ldbkemd": {
        "CT": {
            "test": {
                "MisclassificationRate": 0.07707707707707707,
                "MulticlassPrecision{MLJBase.MacroAvg, OrderedCollections.LittleDict}": 0.9230185549546053,
                "MulticlassTruePositiveRate{MLJBase.MacroAvg, OrderedCollections.LittleDict}": 0.9229229229229229
            },
            "train": {
                "MisclassificationRate": 0.0,
                "MulticlassPrecision{MLJBase.MacroAvg, OrderedCollections.LittleDict}": 1.0,
                "MulticlassTruePositiveRate{MLJBase.MacroAvg, OrderedCollections.LittleDict}": 1.0
            }
        },
        "LDA": {
            "test": {
                "MisclassificationRate": 0.13813813813813813,
                "MulticlassPrecision{MLJBase.MacroAvg, OrderedCollections.LittleDict}": 0.8665985856830274,
                "MulticlassTruePositiveRate{MLJBase.MacroAvg, OrderedCollections.LittleDict}": 0.8618618618618618
            },
            "train": {
                "MisclassificationRate": 0.12121212121212122,
                "MulticlassPrecision{MLJBase.MacroAvg, OrderedCollections.LittleDict}": 0.8828282828282829,
                "MulticlassTruePositiveRate{MLJBase.MacroAvg, OrderedCollections.LittleDict}": 0.8787878787878789
            }
        }
    }
}
