{
    "original": {
        "CT": {
            "test": {
                "MisclassificationRate": 0.16416416416416416,
                "MulticlassPrecision{MLJBase.MacroAvg, OrderedCollections.LittleDict}": 0.8352121801101393,
                "MulticlassTruePositiveRate{MLJBase.MacroAvg, OrderedCollections.LittleDict}": 0.8358358358358359
            },
            "train": {
                "MisclassificationRate": 0.0,
                "MulticlassPrecision{MLJBase.MacroAvg, OrderedCollections.LittleDict}": 1.0,
                "MulticlassTruePositiveRate{MLJBase.MacroAvg, OrderedCollections.LittleDict}": 1.0
            }
        },
        "LDA": {
            "test": {
                "MisclassificationRate": 0.4034034034034034,
                "MulticlassPrecision{MLJBase.MacroAvg, OrderedCollections.LittleDict}": 0.5984196526053152,
                "MulticlassTruePositiveRate{MLJBase.MacroAvg, OrderedCollections.LittleDict}": 0.5965965965965966
            },
            "train": {
                "MisclassificationRate": 0.0,
                "MulticlassPrecision{MLJBase.MacroAvg, OrderedCollections.LittleDict}": 1.0,
                "MulticlassTruePositiveRate{MLJBase.MacroAvg, OrderedCollections.LittleDict}": 1.0
            }
        }
    },
    "ldbk": {
        "CT": {
            "test": {
                "MisclassificationRate": 0.11611611611611612,
                "MulticlassPrecision{MLJBase.MacroAvg, OrderedCollections.LittleDict}": 0.8853311569879634,
                "MulticlassTruePositiveRate{MLJBase.MacroAvg, OrderedCollections.LittleDict}": 0.8838838838838838
            },
            "train": {
                "MisclassificationRate": 0.0,
                "MulticlassPrecision{MLJBase.MacroAvg, OrderedCollections.LittleDict}": 1.0,
                "MulticlassTruePositiveRate{MLJBase.MacroAvg, OrderedCollections.LittleDict}": 1.0
            }
        },
        "LDA": {
            "test": {
                "MisclassificationRate": 0.1001001001001001,
                "MulticlassPrecision{MLJBase.MacroAvg, OrderedCollections.LittleDict}": 0.9010880316518298,
                "MulticlassTruePositiveRate{MLJBase.MacroAvg, OrderedCollections.LittleDict}": 0.8998998998998999
            },
            "train": {
                "MisclassificationRate": 0.09090909090909091,
                "MulticlassPrecision{MLJBase.MacroAvg, OrderedCollections.LittleDict}": 0.9121863799283154,
                "MulticlassTruePositiveRate{MLJBase.MacroAvg, OrderedCollections.LittleDict}": 0.9090909090909092
            }
        }
    },
    "ldbkash": {
        "CT": {
            "test": {
                "MisclassificationRate": 0.32232232232232233,
                "MulticlassPrecision{MLJBase.MacroAvg, OrderedCollections.LittleDict}": 0.6751326999420135,
                "MulticlassTruePositiveRate{MLJBase.MacroAvg, OrderedCollections.LittleDict}": 0.6776776776776777
            },
            "train": {
                "MisclassificationRate": 0.0,
                "MulticlassPrecision{MLJBase.MacroAvg, OrderedCollections.LittleDict}": 1.0,
                "MulticlassTruePositiveRate{MLJBase.MacroAvg, OrderedCollections.LittleDict}": 1.0
            }
        },
        "LDA": {
            "test": {
                "MisclassificationRate": 0.4184184184184184,
                "MulticlassPrecision{MLJBase.MacroAvg, OrderedCollections.LittleDict}": 0.5756436186810883,
                "MulticlassTruePositiveRate{MLJBase.MacroAvg, OrderedCollections.LittleDict}": 0.5815815815815816
            },
            "train": {
                "MisclassificationRate": 0.24242424242424243,
                "MulticlassPrecision{MLJBase.MacroAvg, OrderedCollections.LittleDict}": 0.7569023569023569,
                "MulticlassTruePositiveRate{MLJBase.MacroAvg, OrderedCollections.LittleDict}": 0.7575757575757575
            }
        }
    },
    "ldbkemd": {
        "CT": {
            "test": {
                "MisclassificationRate": 0.08108108108108109,
                "MulticlassPrecision{MLJBase.MacroAvg, OrderedCollections.LittleDict}": 0.9218882718586634,
                "MulticlassTruePositiveRate{MLJBase.MacroAvg, OrderedCollections.LittleDict}": 0.918918918918919
            },
            "train": {
                "MisclassificationRate": 0.0,
                "MulticlassPrecision{MLJBase.MacroAvg, OrderedCollections.LittleDict}": 1.0,
                "MulticlassTruePositiveRate{MLJBase.MacroAvg, OrderedCollections.LittleDict}": 1.0
            }
        },
        "LDA": {
            "test": {
                "MisclassificationRate": 0.1061061061061061,
                "MulticlassPrecision{MLJBase.MacroAvg, OrderedCollections.LittleDict}": 0.894074394719556,
                "MulticlassTruePositiveRate{MLJBase.MacroAvg, OrderedCollections.LittleDict}": 0.8938938938938938
            },
            "train": {
                "MisclassificationRate": 0.06060606060606061,
                "MulticlassPrecision{MLJBase.MacroAvg, OrderedCollections.LittleDict}": 0.9402852049910874,
                "MulticlassTruePositiveRate{MLJBase.MacroAvg, OrderedCollections.LittleDict}": 0.9393939393939394
            }
        }
    }
}
